T5SummaryPratik/__init__.py
T5SummaryPratik/pipeline.py
T5SummaryPratik/pipeline1.py
T5SummaryPratik/utils.py
T5SummaryPratik/utils1.py
t5summarypratik-0.1.4.dist-info/licenses/LICENSE
t5summarypratik-0.1.4.dist-info/METADATA
t5summarypratik-0.1.4.dist-info/WHEEL
t5summarypratik-0.1.4.dist-info/top_level.txt
t5summarypratik-0.1.4.dist-info/RECORD
