Metadata-Version: 2.4
Name: T5SummaryPratik
Version: 0.1.4
Summary: A summarization pipeline using T5 with evaluation metrics and utilities.
Author: Pratik Chourasia
Requires-Python: >=3.8
License-File: LICENSE
Requires-Dist: transformers>=4.30.0
Requires-Dist: torch>=1.13.0
Requires-Dist: evaluate>=0.4.0
Requires-Dist: nltk>=3.8.1
Requires-Dist: textstat>=0.7.3
Requires-Dist: rouge_score
Requires-Dist: bert_score
Requires-Dist: sacrebleu
Requires-Dist: spacy
Requires-Dist: sentencepiece
Dynamic: author
Dynamic: license-file
Dynamic: requires-dist
Dynamic: requires-python
Dynamic: summary
